{"cameraMode":{"drawMode":0,"name":"Shaded","section":"Shading Mode"},"sceneLighting":false,"audioPlay":false,"sceneViewState":{"showFog":false,"showMaterialUpdate":false,"showSkybox":false,"showFlares":false,"showImageEffects":false,"showParticleSystems":false},"in2DMode":false,"pivot":{"x":-27.04230499267578,"y":0.25,"z":-22.182899475097658},"rotation":{"x":-0.08420770615339279,"y":0.9087958931922913,"z":-0.22416670620441438,"w":-0.3416846990585327},"size":5.7157673835754398,"orthographic":false}